kubric/__init__.py
kubric/file_io.py
kubric/kubric_typing.py
kubric/plotting.py
kubric/post_processing.py
kubric/randomness.py
kubric/redirect_io.py
kubric/utils.py
kubric/assets/__init__.py
kubric/assets/asset_preprocessing.py
kubric/assets/asset_source.py
kubric/assets/utils.py
kubric/core/__init__.py
kubric/core/assets.py
kubric/core/cameras.py
kubric/core/color.py
kubric/core/lights.py
kubric/core/materials.py
kubric/core/objects.py
kubric/core/scene.py
kubric/core/traits.py
kubric/core/view.py
kubric/datasets/__init__.py
kubric/datasets/movid.py
kubric/datasets/utils.py
kubric/renderer/__init__.py
kubric/renderer/blender.py
kubric/renderer/blender_utils.py
kubric/safeimport/__init__.py
kubric/safeimport/bpy.py
kubric/simulator/__init__.py
kubric/simulator/pybullet.py
kubric/sunds/__init__.py
kubric/sunds/kubric_builder.py
kubric/sunds/kubric_builder_test.py
kubric/sunds/render_mock_utils.py
test/__init__.py
test/test_blender.py
test/test_cameras.py
test/test_color.py
test/test_core.py
test/test_fileio.py
test/test_postprocessing.py
test/test_pybullet.py
test/test_scene.py
test/test_traits.py
kubric_nightly-2023.12.27.dist-info/LICENSE
kubric_nightly-2023.12.27.dist-info/METADATA
kubric_nightly-2023.12.27.dist-info/WHEEL
kubric_nightly-2023.12.27.dist-info/top_level.txt
kubric_nightly-2023.12.27.dist-info/RECORD
