Metadata-Version: 2.1
Name: kubric-nightly
Version: 2023.12.27
Summary: A data generation pipeline for creating semi-realistic synthetic multi-object videos with rich annotations such as instance segmentation, depth maps, and optical flow.
Home-page: https://github.com/google-research/kubric
Author: Kubric team
Author-email: kubric+dev@google.com
License: Apache 2.0
Classifier: Development Status :: 2 - Pre-Alpha
Classifier: Programming Language :: Python :: 3.9
Classifier: Intended Audience :: Developers
Classifier: Intended Audience :: Science/Research
Classifier: License :: OSI Approved :: Apache Software License
Classifier: Topic :: Multimedia :: Graphics :: 3D Rendering
Classifier: Topic :: Scientific/Engineering :: Artificial Intelligence
Requires-Python: >=3.9
License-File: LICENSE
Requires-Dist: apache-beam[gcp]
Requires-Dist: bidict
Requires-Dist: dataclasses
Requires-Dist: etils[epath_no_tf]
Requires-Dist: cloudml-hypertune
Requires-Dist: google-cloud-storage
Requires-Dist: imageio
Requires-Dist: munch
Requires-Dist: numpy >=1.17
Requires-Dist: pandas
Requires-Dist: pypng
Requires-Dist: pyquaternion
Requires-Dist: python-Levenshtein
Requires-Dist: scikit-learn
Requires-Dist: singledispatchmethod
Requires-Dist: tensorflow
Requires-Dist: tensorflow-datasets >=4.1.0
Requires-Dist: traitlets
Requires-Dist: trimesh
